Metabokiller/Apoptosis_KNN.sav
Metabokiller/Apoptosis_features.csv
Metabokiller/Electrophile_MLP.pkl
Metabokiller/Electrophile_features.csv
Metabokiller/Ensemble-model_KFold0train-data.csv
Metabokiller/Ensemble-model_KFold10train-data.csv
Metabokiller/Ensemble-model_KFold11train-data.csv
Metabokiller/Ensemble-model_KFold12train-data.csv
Metabokiller/Ensemble-model_KFold13train-data.csv
Metabokiller/Ensemble-model_KFold14train-data.csv
Metabokiller/Ensemble-model_KFold15train-data.csv
Metabokiller/Ensemble-model_KFold16train-data.csv
Metabokiller/Ensemble-model_KFold17train-data.csv
Metabokiller/Ensemble-model_KFold18train-data.csv
Metabokiller/Ensemble-model_KFold19train-data.csv
Metabokiller/Ensemble-model_KFold1train-data.csv
Metabokiller/Ensemble-model_KFold2train-data.csv
Metabokiller/Ensemble-model_KFold3train-data.csv
Metabokiller/Ensemble-model_KFold4train-data.csv
Metabokiller/Ensemble-model_KFold5train-data.csv
Metabokiller/Ensemble-model_KFold6train-data.csv
Metabokiller/Ensemble-model_KFold7train-data.csv
Metabokiller/Ensemble-model_KFold8train-data.csv
Metabokiller/Ensemble-model_KFold9train-data.csv
Metabokiller/EnsembleMK.py
Metabokiller/Ensmb_GBC_KFold0.sav
Metabokiller/Ensmb_GBC_KFold1.sav
Metabokiller/Ensmb_GBC_KFold10.sav
Metabokiller/Ensmb_GBC_KFold11.sav
Metabokiller/Ensmb_GBC_KFold12.sav
Metabokiller/Ensmb_GBC_KFold13.sav
Metabokiller/Ensmb_GBC_KFold14.sav
Metabokiller/Ensmb_GBC_KFold15.sav
Metabokiller/Ensmb_GBC_KFold16.sav
Metabokiller/Ensmb_GBC_KFold17.sav
Metabokiller/Ensmb_GBC_KFold18.sav
Metabokiller/Ensmb_GBC_KFold19.sav
Metabokiller/Ensmb_GBC_KFold2.sav
Metabokiller/Ensmb_GBC_KFold3.sav
Metabokiller/Ensmb_GBC_KFold4.sav
Metabokiller/Ensmb_GBC_KFold5.sav
Metabokiller/Ensmb_GBC_KFold6.sav
Metabokiller/Ensmb_GBC_KFold7.sav
Metabokiller/Ensmb_GBC_KFold8.sav
Metabokiller/Ensmb_GBC_KFold9.sav
Metabokiller/Epigenetic_svm.pkl
Metabokiller/Epigenetics_features.csv
Metabokiller/Genomic_Instability_features.csv
Metabokiller-0.2.dist-info/LICENSE
Metabokiller-0.2.dist-info/METADATA
Metabokiller-0.2.dist-info/WHEEL
Metabokiller-0.2.dist-info/top_level.txt
Metabokiller-0.2.dist-info/RECORD
