Metadata-Version: 2.1
Name: Metabokiller
Version: 0.2
Home-page: https://github.com/the-ahuja-lab/Metabokiller
Author: Sanjay Kumar Mohanty
Author-email: sanjaym@iiitd.ac.in
Classifier: Programming Language :: Python :: 3
Classifier: License :: OSI Approved :: MIT License
Classifier: Operating System :: OS Independent
Requires-Python: >=3.7
License-File: LICENSE
